odoo/addons/rental_product_pack/README.rst
odoo/addons/rental_product_pack/__init__.py
odoo/addons/rental_product_pack/__manifest__.py
odoo/addons/rental_product_pack/README/CONTRIBUTORS.rst
odoo/addons/rental_product_pack/README/DESCRIPTION.rst
odoo/addons/rental_product_pack/README/HISTORY.rst
odoo/addons/rental_product_pack/README/USAGE.rst
odoo/addons/rental_product_pack/i18n/de.po
odoo/addons/rental_product_pack/i18n/rental_product_pack.pot
odoo/addons/rental_product_pack/models/__init__.py
odoo/addons/rental_product_pack/models/product.py
odoo/addons/rental_product_pack/models/sale.py
odoo/addons/rental_product_pack/models/stock.py
odoo/addons/rental_product_pack/security/ir.model.access.csv
odoo/addons/rental_product_pack/static/description/icon.png
odoo/addons/rental_product_pack/static/description/index.html
odoo/addons/rental_product_pack/tests/__init__.py
odoo/addons/rental_product_pack/tests/test_rental_product_pack.py
odoo/addons/rental_product_pack/views/product_pack_line_view.xml
odoo/addons/rental_product_pack/views/product_view.xml
odoo14_addon_rental_product_pack-14.0.1.0.1.dist-info/METADATA
odoo14_addon_rental_product_pack-14.0.1.0.1.dist-info/WHEEL
odoo14_addon_rental_product_pack-14.0.1.0.1.dist-info/top_level.txt
odoo14_addon_rental_product_pack-14.0.1.0.1.dist-info/RECORD
